.gitignore
LICENSE.md
README.rst
setup.py
test-requirements.txt
corpushash/__init__.py
corpushash/hashers.py
corpushash.egg-info/PKG-INFO
corpushash.egg-info/SOURCES.txt
corpushash.egg-info/dependency_links.txt
corpushash.egg-info/top_level.txt
notebooks/LSI-twitter.ipynb
notebooks/benchmark.ipynb
notebooks/brazilian.txt
notebooks/tf-idf.ipynb
notebooks/tutorial.ipynb
tests/__init__.py
tests/test_hashers.py