Metadata-Version: 1.1
Name: corpushash
Version: 0.1.0
Summary: Cryptographic hasher of text document corpora
Home-page: https://github.com/NAMD/corpushash
Author: Bruno Cuconato
Author-email: bcclaro+corpushash@gmail.com
License: UNKNOWN
Keywords: python 3,nlp,hash,hashing
Platform: UNKNOWN
Classifier: Development Status :: 3 - Alpha
Classifier: Intended Audience :: Developers
Classifier: Topic :: Software Development :: Build Tools
Classifier: License :: OSI Approved :: GNU Lesser General Public License v3 (LGPLv3)
Classifier: Programming Language :: Python :: 3
Classifier: Programming Language :: Python :: 3.3
Classifier: Programming Language :: Python :: 3.4
Classifier: Programming Language :: Python :: 3.5
